turta_iothat3/Turta_Accel.py
turta_iothat3/Turta_Analog.py
turta_iothat3/Turta_Button.py
turta_iothat3/Turta_Buzzer.py
turta_iothat3/Turta_Digital.py
turta_iothat3/Turta_IRRemote.py
turta_iothat3/Turta_Light.py
turta_iothat3/Turta_Photocoupler.py
turta_iothat3/Turta_Relay.py
turta_iothat3/__init__.py
turta_iothat3-1.0.0.dist-info/LICENCE
turta_iothat3-1.0.0.dist-info/METADATA
turta_iothat3-1.0.0.dist-info/WHEEL
turta_iothat3-1.0.0.dist-info/top_level.txt
turta_iothat3-1.0.0.dist-info/RECORD
